parsr_client/__init__.py
parsr_client/parsr_client.py
parsr_client/parsr_output_interpreter.py
parsr_client-3.2.3.dist-info/WHEEL
parsr_client-3.2.3.dist-info/METADATA
parsr_client-3.2.3.dist-info/RECORD
