Metadata-Version: 2.1
Name: parsr-client
Version: 3.2.3
Summary: Python client for Parsr - Transforms PDF, Documents and Images into Enriched Structured Data
Home-page: http://par.sr
Author: AXA Group Operations S.A.
Requires-Python: >=3.8,<4.0
Classifier: Programming Language :: Python :: 3
Classifier: Programming Language :: Python :: 3.8
Requires-Dist: diff_match_patch (>=20181111,<20181112)
Requires-Dist: pandas (>=1.0.3,<2.0.0)
Requires-Dist: requests (>=2.23.0,<3.0.0)
Requires-Dist: semver (>=2.9.1,<3.0.0)
Requires-Dist: sxsdiff (>=0.3.0,<0.4.0)
Project-URL: Repository, https://github.com/axa-group/Parsr/tree/develop/clients/python-client
